LICENSE
README.md
pyproject.toml
setup.cfg
setup.py
src/msdss_users_api/__init__.py
src/msdss_users_api/cli.py
src/msdss_users_api/core.py
src/msdss_users_api/defaults.py
src/msdss_users_api/env.py
src/msdss_users_api/managers.py
src/msdss_users_api/models.py
src/msdss_users_api/routers.py
src/msdss_users_api/tools.py
src/msdss_users_api.egg-info/PKG-INFO
src/msdss_users_api.egg-info/SOURCES.txt
src/msdss_users_api.egg-info/dependency_links.txt
src/msdss_users_api.egg-info/entry_points.txt
src/msdss_users_api.egg-info/requires.txt
src/msdss_users_api.egg-info/top_level.txt